{
  "activities": {
    "done": true,
    "processedRows": 46,
    "updatedAt": "2026-04-02T10:20:45.196Z"
  },
  "admins": {
    "done": true,
    "processedRows": 12,
    "updatedAt": "2026-04-02T10:20:45.211Z"
  },
  "amenities": {
    "done": true,
    "processedRows": 36,
    "updatedAt": "2026-04-02T10:20:45.228Z"
  },
  "bulkUpdateLogs": {
    "done": true,
    "processedRows": 3,
    "updatedAt": "2026-04-02T10:20:45.245Z"
  },
  "cancellationPlans": {
    "done": true,
    "processedRows": 8,
    "updatedAt": "2026-04-02T10:20:45.259Z"
  },
  "checklistCategoryMaster": {
    "done": true,
    "processedRows": 14,
    "updatedAt": "2026-04-02T10:20:45.273Z"
  },
  "collections": {
    "done": true,
    "processedRows": 19,
    "updatedAt": "2026-04-02T10:20:45.295Z"
  },
  "coupons": {
    "done": true,
    "processedRows": 52,
    "updatedAt": "2026-04-02T10:20:45.316Z"
  },
  "customers": {
    "done": true,
    "processedRows": 586,
    "updatedAt": "2026-04-02T10:20:45.356Z"
  },
  "listingUsers": {
    "done": true,
    "processedRows": 1,
    "updatedAt": "2026-04-02T10:20:45.370Z"
  },
  "discountPlans": {
    "done": true,
    "processedRows": 2,
    "updatedAt": "2026-04-02T10:20:45.383Z"
  },
  "extraPlans": {
    "done": true,
    "processedRows": 0,
    "updatedAt": "2026-04-02T10:20:45.393Z"
  },
  "faqs": {
    "done": true,
    "processedRows": 25,
    "updatedAt": "2026-04-02T10:20:45.407Z"
  },
  "globalConstants": {
    "done": true,
    "processedRows": 1,
    "updatedAt": "2026-04-02T10:20:45.420Z"
  },
  "issueTypes": {
    "done": true,
    "processedRows": 5,
    "updatedAt": "2026-04-02T10:20:45.434Z"
  },
  "notification_event_types": {
    "done": true,
    "processedRows": 6,
    "updatedAt": "2026-04-02T10:20:45.448Z"
  },
  "photos": {
    "done": true,
    "processedRows": 10283,
    "updatedAt": "2026-04-02T10:20:45.871Z"
  },
  "propertyAuditAreaCategoryMaster": {
    "done": true,
    "processedRows": 8,
    "updatedAt": "2026-04-02T10:20:45.892Z"
  },
  "propertyTypes": {
    "done": true,
    "processedRows": 4,
    "updatedAt": "2026-04-02T10:20:45.906Z"
  },
  "ratePlans": {
    "done": true,
    "processedRows": 0,
    "updatedAt": "2026-04-02T10:20:45.914Z"
  },
  "recentSearches": {
    "done": true,
    "processedRows": 762,
    "updatedAt": "2026-04-02T10:20:45.958Z"
  },
  "safetyHygiene": {
    "done": true,
    "processedRows": 4,
    "updatedAt": "2026-04-02T10:20:45.972Z"
  },
  "settings": {
    "done": true,
    "processedRows": 2,
    "updatedAt": "2026-04-02T10:20:45.985Z"
  },
  "singlePages ": {
    "done": true,
    "processedRows": 0,
    "updatedAt": "2026-04-02T10:20:45.993Z"
  },
  "spaces": {
    "done": true,
    "processedRows": 0,
    "updatedAt": "2026-04-02T10:20:46.002Z"
  },
  "states": {
    "done": true,
    "processedRows": 4,
    "updatedAt": "2026-04-02T10:20:46.015Z"
  },
  "staticImages": {
    "done": true,
    "processedRows": 0,
    "updatedAt": "2026-04-02T10:20:46.024Z"
  },
  "supervisors": {
    "done": true,
    "processedRows": 2,
    "updatedAt": "2026-04-02T10:20:46.038Z"
  },
  "tags": {
    "done": true,
    "processedRows": 4,
    "updatedAt": "2026-04-02T10:20:46.052Z"
  },
  "users": {
    "done": true,
    "processedRows": 291,
    "updatedAt": "2026-04-02T10:20:46.080Z"
  },
  "permanentPriceUpdateLogs": {
    "done": true,
    "processedRows": 10,
    "updatedAt": "2026-04-02T10:20:46.099Z"
  },
  "cancellationPercentages": {
    "done": true,
    "processedRows": 24,
    "updatedAt": "2026-04-02T10:20:46.113Z"
  },
  "checklistItemMaster": {
    "done": true,
    "processedRows": 60,
    "updatedAt": "2026-04-02T10:20:46.128Z"
  },
  "proposals": {
    "done": true,
    "processedRows": 4,
    "updatedAt": "2026-04-02T10:20:46.142Z"
  },
  "discountPlansValues": {
    "done": true,
    "processedRows": 3,
    "updatedAt": "2026-04-02T10:20:46.156Z"
  },
  "notification_templates": {
    "done": true,
    "processedRows": 29,
    "updatedAt": "2026-04-02T10:20:46.176Z"
  },
  "cms": {
    "done": true,
    "processedRows": 5,
    "updatedAt": "2026-04-02T10:20:46.193Z"
  },
  "cities": {
    "done": true,
    "processedRows": 8,
    "updatedAt": "2026-04-02T10:20:46.207Z"
  },
  "activityLogs": {
    "done": true,
    "processedRows": 0,
    "updatedAt": "2026-04-02T10:20:46.215Z"
  },
  "bankDetails": {
    "done": true,
    "processedRows": 0,
    "updatedAt": "2026-04-02T10:20:46.222Z"
  },
  "ownersWallet": {
    "done": true,
    "processedRows": 23,
    "updatedAt": "2026-04-02T10:20:46.237Z"
  },
  "walletTransactions": {
    "done": true,
    "processedRows": 82,
    "updatedAt": "2026-04-02T10:20:46.258Z"
  },
  "areas": {
    "done": true,
    "processedRows": 13,
    "updatedAt": "2026-04-02T10:20:46.272Z"
  },
  "walletWithdrawalRequests": {
    "done": true,
    "processedRows": 0,
    "updatedAt": "2026-04-02T10:20:46.280Z"
  },
  "landmarks": {
    "done": true,
    "processedRows": 0,
    "updatedAt": "2026-04-02T10:20:46.289Z"
  },
  "nearbyLocations": {
    "done": true,
    "processedRows": 0,
    "updatedAt": "2026-04-02T10:20:46.298Z"
  },
  "properties": {
    "done": true,
    "processedRows": 141,
    "updatedAt": "2026-04-02T10:20:46.378Z"
  },
  "searchQuery": {
    "done": true,
    "processedRows": 0,
    "updatedAt": "2026-04-02T10:20:46.386Z"
  },
  "activitiesOnProperties": {
    "done": true,
    "processedRows": 970,
    "updatedAt": "2026-04-02T10:20:46.428Z"
  },
  "amenitiesOnProperties": {
    "done": true,
    "processedRows": 1911,
    "updatedAt": "2026-04-02T10:20:46.500Z"
  },
  "bankDetailsOnProperties": {
    "done": true,
    "processedRows": 0,
    "updatedAt": "2026-04-02T10:20:46.508Z"
  },
  "blockedDates": {
    "done": true,
    "processedRows": 3,
    "updatedAt": "2026-04-02T10:20:46.522Z"
  },
  "bookings": {
    "done": true,
    "processedRows": 490,
    "updatedAt": "2026-04-02T10:20:46.599Z"
  },
  "caretakersOnProperties": {
    "done": true,
    "processedRows": 116,
    "updatedAt": "2026-04-02T10:20:46.614Z"
  },
  "carousel": {
    "done": true,
    "processedRows": 6,
    "updatedAt": "2026-04-02T10:20:46.628Z"
  },
  "collectionProperties": {
    "done": true,
    "processedRows": 730,
    "updatedAt": "2026-04-02T10:20:46.662Z"
  },
  "contactEnquiry": {
    "done": true,
    "processedRows": 0,
    "updatedAt": "2026-04-02T10:20:46.671Z"
  },
  "enquiries": {
    "done": true,
    "processedRows": 4,
    "updatedAt": "2026-04-02T10:20:46.684Z"
  },
  "icalLinks": {
    "done": true,
    "processedRows": 1,
    "updatedAt": "2026-04-02T10:20:46.697Z"
  },
  "managersOnProperties": {
    "done": true,
    "processedRows": 133,
    "updatedAt": "2026-04-02T10:20:46.714Z"
  },
  "ownersOnProperties": {
    "done": true,
    "processedRows": 126,
    "updatedAt": "2026-04-02T10:20:46.730Z"
  },
  "propertyAuditAreas": {
    "done": true,
    "processedRows": 26,
    "updatedAt": "2026-04-02T10:20:46.745Z"
  },
  "propertyAuditSessions": {
    "done": true,
    "processedRows": 18,
    "updatedAt": "2026-04-02T10:20:46.759Z"
  },
  "propertyCancellationPlans": {
    "done": true,
    "processedRows": 248,
    "updatedAt": "2026-04-02T10:20:46.781Z"
  },
  "propertyCoupons": {
    "done": true,
    "processedRows": 0,
    "updatedAt": "2026-04-02T10:20:46.788Z"
  },
  "propertyDiscountPlans": {
    "done": true,
    "processedRows": 125,
    "updatedAt": "2026-04-02T10:20:46.806Z"
  },
  "propertyPhotos": {
    "done": true,
    "processedRows": 10064,
    "updatedAt": "2026-04-02T10:20:47.247Z"
  },
  "property_tags": {
    "done": true,
    "processedRows": 0,
    "updatedAt": "2026-04-02T10:20:47.255Z"
  },
  "proposalItems": {
    "done": true,
    "processedRows": 17,
    "updatedAt": "2026-04-02T10:20:47.268Z"
  },
  "recentlyVisited": {
    "done": true,
    "processedRows": 0,
    "updatedAt": "2026-04-02T10:20:47.284Z"
  },
  "safetyHygieneOnProperties": {
    "done": true,
    "processedRows": 10,
    "updatedAt": "2026-04-02T10:20:47.303Z"
  },
  "spaceProperties": {
    "done": true,
    "processedRows": 0,
    "updatedAt": "2026-04-02T10:20:47.313Z"
  },
  "specialDates": {
    "done": true,
    "processedRows": 4,
    "updatedAt": "2026-04-02T10:20:47.329Z"
  },
  "viewEnquiry": {
    "done": true,
    "processedRows": 0,
    "updatedAt": "2026-04-02T10:20:47.337Z"
  },
  "bookingAuditLog": {
    "done": true,
    "processedRows": 1517,
    "updatedAt": "2026-04-02T10:20:47.411Z"
  },
  "cancellations": {
    "done": true,
    "processedRows": 36,
    "updatedAt": "2026-04-02T10:20:47.423Z"
  },
  "notification_event_log": {
    "done": true,
    "processedRows": 116,
    "updatedAt": "2026-04-02T10:20:47.441Z"
  },
  "payments": {
    "done": true,
    "processedRows": 82,
    "updatedAt": "2026-04-02T10:20:47.463Z"
  },
  "reviewMagicLinks": {
    "done": true,
    "processedRows": 3,
    "updatedAt": "2026-04-02T10:20:47.483Z"
  },
  "reviews": {
    "done": true,
    "processedRows": 0,
    "updatedAt": "2026-04-02T10:20:47.491Z"
  },
  "carouselPhotos": {
    "done": true,
    "processedRows": 12,
    "updatedAt": "2026-04-02T10:20:47.503Z"
  },
  "whatsappLog": {
    "done": true,
    "processedRows": 0,
    "updatedAt": "2026-04-02T10:20:47.509Z"
  },
  "importedBookings": {
    "done": true,
    "processedRows": 3,
    "updatedAt": "2026-04-02T10:20:47.522Z"
  },
  "inventoryChecklistItems": {
    "done": true,
    "processedRows": 60,
    "updatedAt": "2026-04-02T10:20:47.538Z"
  },
  "maintenanceChecklistItems": {
    "done": true,
    "processedRows": 22,
    "updatedAt": "2026-04-02T10:20:47.551Z"
  },
  "suppliesChecklistItems": {
    "done": true,
    "processedRows": 4,
    "updatedAt": "2026-04-02T10:20:47.564Z"
  },
  "tickets": {
    "done": true,
    "processedRows": 12,
    "updatedAt": "2026-04-02T10:20:47.577Z"
  },
  "notification_dead_letter_queue": {
    "done": true,
    "processedRows": 160,
    "updatedAt": "2026-04-02T10:20:47.601Z"
  },
  "notification_delivery_log": {
    "done": true,
    "processedRows": 1172,
    "updatedAt": "2026-04-02T10:20:47.750Z"
  },
  "bookingPaymentSchedule": {
    "done": true,
    "processedRows": 0,
    "updatedAt": "2026-04-02T10:20:47.757Z"
  },
  "inventoryAuditChecklistItems": {
    "done": true,
    "processedRows": 6,
    "updatedAt": "2026-04-02T10:20:47.777Z"
  },
  "maintenanceAuditChecklistItems": {
    "done": true,
    "processedRows": 18,
    "updatedAt": "2026-04-02T10:20:47.790Z"
  },
  "suppliesAuditChecklistItems": {
    "done": true,
    "processedRows": 23,
    "updatedAt": "2026-04-02T10:20:47.803Z"
  },
  "ticketResolutionLogs": {
    "done": true,
    "processedRows": 2,
    "updatedAt": "2026-04-02T10:20:47.815Z"
  },
  "checklistItemMedia": {
    "done": true,
    "processedRows": 23,
    "updatedAt": "2026-04-02T10:20:47.828Z"
  }
}